adcode/__init__.py
adcode/admin.py
adcode/apps.py
adcode/conf.py
adcode/context_processors.py
adcode/models.py
adcode/recievers.py
adcode/validators.py
adcode/views.py
adcode/fixtures/iab_sizes.json
adcode/migrations/0001_initial.py
adcode/migrations/__init__.py
adcode/south_migrations/0001_initial.py
adcode/south_migrations/0002_auto__add_field_section_priority.py
adcode/south_migrations/__init__.py
adcode/templates/adcode/header.html
adcode/templates/adcode/placement.html
adcode/templatetags/__init__.py
adcode/templatetags/adcode_tags.py
adcode/tests/__init__.py
adcode/tests/base.py
adcode/tests/test_context_processors.py
adcode/tests/test_fixtures.py
adcode/tests/test_performance.py
adcode/tests/test_templatetags.py
adcode/tests/test_validators.py
adcode/tests/templates/adcode/header.html
adcode/tests/templates/adcode/placement.html
adcode/tests/templates/adcode/section-1/header.html
adcode/tests/templates/adcode/section-1/placement.html
adcode/tests/templates/adcode/section-1/sidebar-placement.html
django_ad_code-1.0.0.dist-info/DESCRIPTION.rst
django_ad_code-1.0.0.dist-info/METADATA
django_ad_code-1.0.0.dist-info/RECORD
django_ad_code-1.0.0.dist-info/WHEEL
django_ad_code-1.0.0.dist-info/metadata.json
django_ad_code-1.0.0.dist-info/top_level.txt
